CHANGES.txt
MANIFEST.in
README.rst
setup.py
repoze/__init__.py
repoze.who.plugins.digestauth.egg-info/PKG-INFO
repoze.who.plugins.digestauth.egg-info/SOURCES.txt
repoze.who.plugins.digestauth.egg-info/dependency_links.txt
repoze.who.plugins.digestauth.egg-info/namespace_packages.txt
repoze.who.plugins.digestauth.egg-info/not-zip-safe
repoze.who.plugins.digestauth.egg-info/requires.txt
repoze.who.plugins.digestauth.egg-info/top_level.txt
repoze/who/__init__.py
repoze/who/plugins/__init__.py
repoze/who/plugins/digestauth/__init__.py
repoze/who/plugins/digestauth/noncemanager.py
repoze/who/plugins/digestauth/tests.py
repoze/who/plugins/digestauth/utils.py