Metadata-Version: 1.0
Name: repoze.who.plugins.digestauth
Version: 0.1.1
Summary: repoze.who.plugins.digestauth
Home-page: https://github.com/mozilla-services/repoze.who.plugins.digestauth
Author: Mozilla Services
Author-email: services-dev@mozilla.org
License: UNKNOWN
Keywords: authentication repoze http digest
Platform: UNKNOWN
Classifier: Programming Language :: Python
